karboni/__init__.py
karboni/async_utils.py
karboni/cli.py
karboni/exceptions.py
karboni/http.py
karboni/logging_utils.py
karboni/py.typed
karboni/typing.py
karboni/utils.py
karboni/database/__init__.py
karboni/database/engine.py
karboni/database/library.py
karboni/database/schema.py
karboni/zotero/__init__.py
karboni/zotero/config.py
karboni/zotero/delta.py
karboni/zotero/handler.py
karboni/zotero/sync.py
karboni-0.1.0a1.dist-info/METADATA
karboni-0.1.0a1.dist-info/WHEEL
karboni-0.1.0a1.dist-info/entry_points.txt
karboni-0.1.0a1.dist-info/licenses/LICENSE.txt
karboni-0.1.0a1.dist-info/RECORD
