Metadata-Version: 2.4
Name: Karboni
Version: 0.1.0a1
Summary: Mirror a Zotero library into a SQL database
Project-URL: Documentation, https://github.com/whiskyechobravo/karboni/blob/main/README.md
Project-URL: Code, https://github.com/whiskyechobravo/karboni
Project-URL: Changes, https://github.com/whiskyechobravo/karboni/blob/main/CHANGELOG.md
Project-URL: Issues, https://github.com/whiskyechobravo/karboni/issues
Author-email: David Lesieur <karboni@whiskyechobravo.com>
License-Expression: GPL-3.0-only
License-File: LICENSE.txt
Keywords: academia,zotero
Classifier: Development Status :: 3 - Alpha
Classifier: Intended Audience :: Developers
Classifier: Intended Audience :: Education
Classifier: Intended Audience :: Science/Research
Classifier: Operating System :: OS Independent
Classifier: Programming Language :: Python
Classifier: Programming Language :: Python :: 3
Classifier: Programming Language :: Python :: 3.11
Classifier: Programming Language :: Python :: 3.12
Classifier: Programming Language :: Python :: 3.13
Classifier: Programming Language :: Python :: 3.14
Classifier: Topic :: Database :: Front-Ends
Classifier: Topic :: Education
Classifier: Topic :: Scientific/Engineering
Classifier: Topic :: Software Development :: Libraries :: Python Modules
Requires-Python: >=3.11
Requires-Dist: anyio>=4.9.0
Requires-Dist: click-option-group>=0.5.7
Requires-Dist: click>=8.2.1
Requires-Dist: colorlog>=6.10.1
Requires-Dist: httpx>=0.28.1
Requires-Dist: python-dotenv>=1.1.1
Requires-Dist: sqlalchemy>=2.0.41
Provides-Extra: dev
Requires-Dist: mypy>=1.16.1; extra == 'dev'
Requires-Dist: pre-commit>=4.2.0; extra == 'dev'
Requires-Dist: rope>=1.13.0; extra == 'dev'
Requires-Dist: ruff>=0.12.11; extra == 'dev'
